README.md
setup.py
googlemaps/__init__.py
googlemaps/client.py
googlemaps/convert.py
googlemaps/directions.py
googlemaps/distance_matrix.py
googlemaps/elevation.py
googlemaps/exceptions.py
googlemaps/geocoding.py
googlemaps/geolocation.py
googlemaps/places.py
googlemaps/roads.py
googlemaps/timezone.py
googlemaps_nb.egg-info/PKG-INFO
googlemaps_nb.egg-info/SOURCES.txt
googlemaps_nb.egg-info/dependency_links.txt
googlemaps_nb.egg-info/requires.txt
googlemaps_nb.egg-info/top_level.txt
test/test_client.py
test/test_convert.py
test/test_directions.py
test/test_distance_matrix.py
test/test_elevation.py
test/test_geocoding.py
test/test_geolocation.py
test/test_places.py
test/test_roads.py
test/test_timezone.py