Metadata-Version: 1.1
Name: googlemaps-nb
Version: 2.5.1.dev0
Summary: Python client library for Google Maps API Web Services
Home-page: https://github.com/googlemaps/google-maps-services-python
Author: UNKNOWN
Author-email: UNKNOWN
License: Apache 2.0
Platform: Posix; MacOS X; Windows
Classifier: Development Status :: 4 - Beta
Classifier: Intended Audience :: Developers
Classifier: License :: OSI Approved :: Apache Software License
Classifier: Operating System :: OS Independent
Classifier: Programming Language :: Python :: 2.7
Classifier: Programming Language :: Python :: 3.2
Classifier: Programming Language :: Python :: 3.4
Classifier: Programming Language :: Python :: 3.5
Classifier: Programming Language :: Python :: 3.6
Classifier: Topic :: Internet
